{
  "shoppingssss": {
    "active": true,
    "last_incident": 1778073514,
    "incidents": 1,
    "weekly": 1,
    "flaps": 1,
    "downtime": 509,
    "mttr": 509
  },
  "testasssa": {
    "active": false,
    "last_incident": 1778131971,
    "incidents": 2,
    "weekly": 2,
    "flaps": 1,
    "downtime": 58946,
    "mttr": 29473
  },
  "my-web": {
    "active": false,
    "last_incident": 1778131960,
    "incidents": 1,
    "weekly": 1,
    "flaps": 0,
    "downtime": 58411,
    "mttr": 58411
  }
}
